cmip_branded_variable_mapper/__init__.py
cmip_branded_variable_mapper/area_label.py
cmip_branded_variable_mapper/horizontal_label.py
cmip_branded_variable_mapper/mapper.py
cmip_branded_variable_mapper/mapper_classes.py
cmip_branded_variable_mapper/py.typed
cmip_branded_variable_mapper/temporal_label.py
cmip_branded_variable_mapper/vertical_label.py
cmip_branded_variable_mapper-0.13.1.dist-info/WHEEL
cmip_branded_variable_mapper-0.13.1.dist-info/METADATA
cmip_branded_variable_mapper-0.13.1.dist-info/RECORD
