Metadata-Version: 2.3
Name: cmip-branded-variable-mapper
Version: 0.13.1
Summary: Mapping from CMIP variable and other information to branded variable names.
Author: Zebedee Nicholls, Annika Hoegner, Niklas Schwind, Tessa Moeller
Author-email: Zebedee Nicholls <zebedee.nicholls@climate-energy-college.org>, Annika Hoegner <hoegner@iiasa.ac.at>, Niklas Schwind <schwind@iiasa.ac.at>, Tessa Moeller <moeller@iiasa.ac.at>
License: placeholder
Classifier: Development Status :: 3 - Alpha
Classifier: Intended Audience :: Science/Research
Classifier: Natural Language :: English
Classifier: Operating System :: OS Independent
Classifier: Programming Language :: Python
Classifier: Programming Language :: Python :: 3
Classifier: Programming Language :: Python :: 3 :: Only
Classifier: Programming Language :: Python :: 3.9
Classifier: Programming Language :: Python :: 3.10
Classifier: Programming Language :: Python :: 3.11
Classifier: Programming Language :: Python :: 3.12
Classifier: Programming Language :: Python :: 3.13
Classifier: Typing :: Typed
Requires-Dist: attrs>=24.3.0
Requires-Dist: openpyxl>=3.1.5
Requires-Dist: pandas>=2.2.3
Requires-Dist: numpy>=1.26.0 ; python_full_version < '3.13'
Requires-Dist: numpy>=2.1.0 ; python_full_version >= '3.13'
Requires-Dist: tabulate>=0.9.0
Requires-Dist: attrs==25.3.0 ; extra == 'locked'
Requires-Dist: et-xmlfile==2.0.0 ; extra == 'locked'
Requires-Dist: numpy==2.0.2 ; python_full_version < '3.10' and extra == 'locked'
Requires-Dist: numpy==2.2.3 ; python_full_version >= '3.10' and extra == 'locked'
Requires-Dist: openpyxl==3.1.5 ; extra == 'locked'
Requires-Dist: pandas==2.2.3 ; extra == 'locked'
Requires-Dist: python-dateutil==2.9.0.post0 ; extra == 'locked'
Requires-Dist: pytz==2025.1 ; extra == 'locked'
Requires-Dist: six==1.17.0 ; extra == 'locked'
Requires-Dist: tabulate==0.9.0 ; extra == 'locked'
Requires-Dist: tzdata==2025.1 ; extra == 'locked'
Requires-Python: >=3.9
Project-URL: Changelog, https://cmip-branded-variable-mapper.readthedocs.io/en/stable/changelog
Project-URL: Documentation, https://cmip-branded-variable-mapper.readthedocs.io
Project-URL: Homepage, https://cmip-branded-variable-mapper.readthedocs.io
Project-URL: Issues, https://github.com/znicholls/CMIP-branded-variables-mapper/issues
Project-URL: Repository, https://github.com/znicholls/CMIP-branded-variables-mapper
Provides-Extra: locked
